mycwl/__init__.py
mycwl/cwl.py
mycwl/exceptions.py
mycwl/setup.py
mycwl-0.0.1.dist-info/METADATA
mycwl-0.0.1.dist-info/WHEEL
mycwl-0.0.1.dist-info/top_level.txt
mycwl-0.0.1.dist-info/RECORD
